single-cycle_RISC-V_model/rom.sv
module rom #(parameter WAD = 8, WD = 8)(
    input logic [WAD-1: 0] AddrIn,
    output logic [WD*4-1: 0] DOut
);

logic [WD-1: 0] RomArr [2**WAD-1: 0]; // error occurs if 2^32 is used

initial begin
    $readmemh("rom2.mem", RomArr);
end;

assign DOut = {RomArr[AddrIn], RomArr[AddrIn+1], RomArr[AddrIn+2], RomArr[AddrIn+3]};

endmodule

single_cycle-RISC-V/PCReg.sv
module PCReg #(parameter W = 32)(
    input logic clk,
    input logic rst,
    input logic [W-1: 0] PCN,
    output logic [W-1: 0] PC
);

always_ff@(posedge clk)
    if (rst) PC <= {W{1'b0}};
    else PC <= PCN;

endmodule

single-cycle_RISC-V_model/datapath2.sv
module datapath2 #(parameter W = 32)(
    input logic clk,
    input logic rst,
    input logic [1:0] PCsrc,
    input logic [W-1:0] IMMop,
    input logic [W-1:0] DOutAlu,

    output logic [W-1:0] PC,
    output logic [W-1:0] instr
);

logic [W-1:0] PCN;
logic [W-1:0] branch_pc;

assign branch_pc = PC + IMMop;

always_comb 
case (PCsrc)

    2'b00: PCN = PC + 4;
    2'b01: PCN = branch_pc;
    2'b11: PCN = DOutAlu;
    default: PCN = PC + 4;
endcase

pcreg P1(
    .clk(clk),
    .rst(rst),
    .PCN(PCN),

    .PC(PC)
);

rom R1(
    .AddrIn(PC),

    .DOut(instr)
);


endmodule

single-cycle_RISC-V_model/control.sv
module control #(parameter W = 32)(
    input logic [W-1:0] instr,
    input logic flag,
    output logic RegWrite,
    output logic RamWrite,
    output logic [1:0] ALUop,
    output logic ALUsrc,
    output logic [2:0] IMMsrc,
    output logic [1:0] PCsrc,
    output logic [1:0] ResultSrc
);

/*
name    parameter       |   op      func3   func7       explanation

Already tested instructions:

addi    Rd, Ra, IMM12   |   0010011 000     x
slli    Rd, Ra, IMM12   |   0110011 001     x
slti    Rd, Ra, IMM12   |   0110011 010     x
xori    Rd, Ra, IMM12   |   0110011 100     x
srli    Rd, Ra, IMM12   |   0110011 101     x
ori     Rd, Ra, IMM12   |   0110011 110     x
andi    Rd, Ra, IMM12   |   0110011 111     x

add     Rd, Ra, Rb      |   0110011 000     0000000 
sub     Rd, Ra, Rb      |   0110011 000     0100000
sll     Rd, Ra, Rb      |   0110011 001     0000000     logic shift left
slt     Rd, Ra, Rb      |   0110011 010     0000000     set less than
xor     Rd, Ra, Rb      |   0110011 100     0000000
srl     Rd, Ra, Rb      |   0110011 101     0000000     logic shift right
or      Rd, Ra, Rb      |   0110011 110     0000000
and     Rd, Ra, Rb      |   0110011 111     0000000

lui     Rd, IMM20       |   0110111 x       x

bne     Rd, Ra, IMM     |   1100011 001     x
bnez    Rd, Ra, IMM     |
beq     Rd, Ra, IMM     |   1100011 000     x
blt     Rd, Ra, IMM     |   1100011 100     x
bge     Rd, Ra, IMM     |   1100011 101     x

sb      Rb, IMM12(Ra)   |   0100011 000     x
sh      Rb, IMM12(Ra)   |   0000011 001     x
sw      Rb, IMM12(Ra)   |   0100011 010     x

lb      Rd, IMM12(Ra)   |   0000011 000     x
lh      Rd, IMM12(Ra)   |   0000011 001     x
lw      Rd, IMM12(Ra)   |   0000011 010     x
lbu     Rd, IMM12(Ra)   |   0000011 100     x
lhu     Rd, IMM12(Ra)   |   0000011 101     x

jal     Rd, IMM20       |   1101111 x       x
jalr    Rd, Ra, IMM12   |   1100111 000     x           actually belongs to i-type

under-testing instructions:

bltu    Rd, Ra, IMM     |   1100011 110     x
bgeu    Rd, Ra, IMM     |   1100011 111     x
sltu    Rd, Ra, Rb      |   0110011 011     0000000     
sra     Rd, Ra, Rb      |   0110011 101     0100000     arithmetic shift left

*/

logic [6:0] op7;

logic [1:0] PCsrc_req1;

always_comb begin
    op7 = instr[W-26:W-32];
end

// to imm.sv
always_comb 
case (op7)
    7'b0010011: IMMsrc = 3'b000; // i-type
    7'b0000011: IMMsrc = 3'b000; 
    7'b1100111: IMMsrc = 3'b000; // jalr

    7'b0100011: IMMsrc = 3'b001; // s-type

    7'b1100011: IMMsrc = 3'b010; // b-type

    7'b0110111: IMMsrc = 3'b011; // u-type
    7'b0010111: IMMsrc = 3'b011;

    
    7'b1101111: IMMsrc = 3'b100; // j-type

    default: IMMsrc = 3'b000;
endcase

// to alu.sv
always_comb 
case (op7)
    7'b0100011: ALUsrc = 1'b1; // s-type
    7'b0010011: ALUsrc = 1'b1; // i-type
    7'b0000011: ALUsrc = 1'b1; 
    7'b1100111: ALUsrc = 1'b1; // jalr
    7'b0110111: ALUsrc = 1'b1; // u-type
endcase

// to datapath1.sv
always_comb 
case (op7)
    7'b0100011: ALUop = 2'b00; // s-type
    7'b0000011: ALUop = 2'b00; // load

    7'b1100011: ALUop = 2'b01; // b-type

    7'b0010011: ALUop = 2'b10; // i-type
    
    7'b0110011: ALUop = 2'b10; // r-type

    7'b1101111: ALUop = 2'b11; // j-type
    7'b1100111: ALUop = 2'b11; // jalr

    default: ALUop = 2'b00;
endcase

// to reg32.sv
always_comb 
case (op7)
    7'b0110011: RegWrite = 1'b1; // r-type
    7'b0010011: RegWrite = 1'b1; // i-type
    7'b0000011: RegWrite = 1'b1;
    7'b0110111: RegWrite = 1'b1; // u-type
    7'b0010111: RegWrite = 1'b1;
    7'b1100111: RegWrite = 1'b1; // jalr
    7'b1101111: RegWrite = 1'b1; // j-type
    default: RegWrite = 1'b0;
endcase

// to datapath2.sv
always_comb 
case (op7)
    7'b1100011: PCsrc_req1 = 2'b01; // b-type
    7'b1101111: PCsrc_req1 = 2'b01; // j-type
    7'b1100111: PCsrc_req1 = 2'b11; // jalr
    default: PCsrc_req1 = 2'b00;
endcase



always_comb 
case (op7)
    7'b0100011: RamWrite = 1'b1; // s-type
    default: RamWrite = 1'b0;
endcase

always_comb begin
    PCsrc = {PCsrc_req1[1], {PCsrc_req1[0] && flag}};
end

always_comb 
case (op7)
    7'b0000011: ResultSrc = 2'b01; // load
    7'b1101111: ResultSrc = 2'b10; // j-type
    7'b0110111: ResultSrc = 2'b11; // u-type
    default: ResultSrc = 2'b00;
endcase

endmodule

single-cycle_RISC-V_model/ram.sv
module ram #(parameter WA = 32, WAM = 18, WB = 8, WD = 32)(
    input logic clk,
    input logic [WA-1:0] Ad,
    input logic RamWrite,
    input logic [2:0] func3,
    input logic [WD-1:0] DIn,
    output logic [WD-1:0] DOut
);
                 
logic [WB-1:0] RamArray [2**WAM-1:0]; // stored in byte
logic [WAM-1:0] AdM; // reduced in size, 2**32 is too large to simulate

logic [WD-1:0] show; // used for testing

initial begin
    $readmemh("triangle.mem", RamArray);
end;

always_comb begin 
    AdM = Ad[WAM-1:0];
    case (func3) 
        3'b000: DOut = {{24{RamArray[AdM][WB-1]}},RamArray[AdM]}; // lb
        3'b001: DOut = {{16{RamArray[AdM][WB-1]}},RamArray[AdM], RamArray[AdM+1]}; // lh
        3'b010: DOut = {RamArray[AdM], RamArray[AdM+1], RamArray[AdM+2], RamArray[AdM+3]}; // lw
        3'b100: DOut = {{24'b0},RamArray[AdM]}; // lbu
        3'b101: DOut = {{16'b0},RamArray[AdM], RamArray[AdM+1]}; // lhu
        default: DOut = {RamArray[AdM], RamArray[AdM+1], RamArray[AdM+2], RamArray[AdM+3]}; // lw
    endcase
end

always_ff@(posedge clk)
    if (RamWrite) 
    begin
        if (func3[1:0] == 2'b10)
        begin
            RamArray[AdM] <= DIn[WD-1:WD-8];
            RamArray[AdM+1] <= DIn[WD-9:WD-16];
            RamArray[AdM+2] <= DIn[WD-17:WD-24];
            RamArray[AdM+3] <= DIn[WD-25:0];
        end
        else if (func3[1:0] == 2'b01)
        begin
            RamArray[AdM] <= DIn[WD-17:WD-24];
            RamArray[AdM+1] <= DIn[WD-25:0];
        end
        else if (func3[1:0] == 2'b00) RamArray[AdM] <= DIn[WD-25:0];
    end

assign show = {RamArray[16], RamArray[17], RamArray[18], RamArray[19]};

endmodule

single-cycle_RISC-V_model/imm.sv
module imm #(parameter W = 32)(
    input logic [2:0] IMMsrc,
    input logic [W-1:0] instr,
    output logic [W-1:0] out
);

logic sign; // for 2's complement

assign sign = instr[W-1]; // not required by extend (U / J type)

always_comb case(IMMsrc)
    3'b000: out = {{20{sign}}, instr[W-1:W-12]}; // I-type
    3'b001: out = {{20{sign}}, instr[W-1:W-7], instr[W-21:W-25]}; // S-type
    3'b010: out = {{19{sign}}, instr[W-1], instr[W-25], instr[W-2:W-7], instr[W-21:W-24], 1'b0}; //B-type
    3'b011: out = {instr[W-1:W-20], 12'b0}; // U-type
    3'b100: out = {{11{sign}}, instr[W-1], instr[W-13:W-20], instr[W-12], instr[W-2:W-11], 1'b0}; // J-type
    default: out = {{20{sign}}, instr[W-1:W-12]}; // I-type
endcase

endmodule

single-cycle_RISC-V_model/aluflagdecode.sv
module aluflagdecode (
    input logic [2:0] func3,
    input logic [1:0] ALUop,
    output logic [2:0] ALUflag
);

always_comb
case (func3)
    3'b000: ALUflag = 3'b000; // beq
    3'b001: ALUflag = 3'b001; // bne
    3'b100: ALUflag = 3'b101; // blt
    3'b101: ALUflag = 3'b100; // bge
    3'b110: ALUflag = 3'b111; // bltu
    3'b111: ALUflag = 3'b011; // bgeu

    default: ALUflag = 3'b010;
endcase

always_comb begin
    if (ALUop == 2'b11) ALUflag = 3'b011;
end
    
endmodule

single-cycle_RISC-V_model/aludecode.sv
module aludecode (
    input logic [2:0] func3,
    input logic [1:0] ALUop,
    input logic func75,
    input logic op5,
    output logic [2:0] ALUctrl
);

always_comb
case (func3)
    3'b001: ALUctrl = 3'b110; // sla
    3'b010: ALUctrl = 3'b101; // slt
    3'b011: ALUctrl = 3'b101; // sltu
    3'b100: ALUctrl = 3'b100; // xor
    3'b101: ALUctrl = 3'b111; // sll
    3'b110: ALUctrl = 3'b011; // or
    3'b111: ALUctrl = 3'b010; // and


    default: ALUctrl = 3'b000;
endcase

always_comb
case ({func3, op5, func75})
    5'b00011: ALUctrl = 3'b001;
    5'b00000: ALUctrl = 3'b000;
    5'b00001: ALUctrl = 3'b000;
    5'b00010: ALUctrl = 3'b000;
    default: ALUctrl = ALUctrl;
endcase

always_comb
case (ALUop)
    2'b00: ALUctrl = 3'b000;
    2'b01: ALUctrl = 3'b001;
    2'b11: ALUctrl = 3'b000;
    default: ALUctrl = ALUctrl;
endcase
    
endmodule

single-cycle_RISC-V_model/alu.sv
module alu #(parameter W = 32)(
    input logic [2: 0] ALUctrl,
    input logic [2: 0] ALUflag,
    input logic [W-1: 0] N1,
    input logic [W-1: 0] N2,
    output logic [W-1: 0] out,
    output logic flag
);

always_comb
    case (ALUctrl)
        3'b000: out = N1 + N2; // add
        3'b001: out = N1 - N2; // sub
        3'b010: out = N1 & N2; // and
        3'b011: out = N1 | N2; // or
        3'b100: out = N1 ^ N2; // xor
        3'b101: out = (N1 < N2) ? 32'b1 : 32'b0; // set less than, slt
        3'b110: out = N1 << N2;  // sll
        3'b111: out = N1 >> N2;  // srl

        default out = N1 + N2;
    endcase

always_comb 
    case (ALUflag)
        3'b000: flag = (out == 0)? 1 : 0; // beq
        3'b001: flag = (out != 0)? 1 : 0; // bne
        3'b010: flag = 0;
        3'b011: flag = 1;
        3'b100: flag = (out < 0)? 1 : 0; // blt
        3'b101: flag = (out >= 0)? 1 : 0; // bge
        3'b110: flag = (out < 0)? 1 : 0; // bltu
        3'b111: flag = (out >= 0)? 1 : 0; // bgeu

        default flag = 0;
    endcase

endmodule

single-cycle_RISC-V_model/reg32.sv
module reg32 #(parameter WAD = 5, WD = 32, R0 = 10)( // A0 = reg[10] or reg 01010
    input logic clk,
    input logic RegWrite,
    input logic [WAD-1:0] AdIn,
    input logic [WAD-1:0] AdOut1,
    input logic [WAD-1:0] AdOut2,
    output logic [WD-1:0] DIn,
    output logic [WD-1:0] DOut1,
    output logic [WD-1:0] DOut2,
    output logic [WD-1:0] A0
);

logic [WD-1: 0] RomArr [2**WAD-1: 0];

always_ff@(posedge clk)
    if (RegWrite) RomArr[AdIn] <= DIn;

assign RomArr[0] = 32'b0;

assign DOut1 = RomArr[AdOut1];
assign DOut2 = RomArr[AdOut2];

assign A0 = RomArr[R0];

endmodule

/* 
x0  	zero	Always zero	
x1      ra	    Return address	
x2	    sp	    Stack pointer
x3	    gp	    Global pointer	
x4	    tp	    Thread pointer	
x5	    t0	    Temporary / alternate return address
x6–7	t1–2	Temporaries
x8	    s0/fp	Saved register / frame pointer
x9	    s1	    Saved register
x10–11	a0–1	Function arguments / return values
x12–17	a2–7	Function arguments
x18–27	s2–11	Saved registers
x28–31	t3–6	Temporaries

32 floating-point extension registers

f0–7	ft0–7	Floating-point temporaries
f8–9	fs0–1	Floating-point saved registers
f10–11	fa0–1	Floating-point arguments/return values
f12–17	fa2–7	Floating-point arguments
f18–27	fs2–11	Floating-point saved registers
f28–31	ft8–11	Floating-point temporaries
*/

single-cycle_RISC-V_model/datapath1.sv
module datapath1 #(parameter WAD = 5, WD = 32)(
    input logic clk,

    input logic [WAD-1:0] AdIn,
    input logic [WAD-1:0] AdOut1,
    input logic [WAD-1:0] AdOut2,
    input logic [WD-1:0] instr,

    input logic [WD-1:0] PC,

    input logic ALUsrc,
    input logic [1:0] ALUop,
    input logic [1:0] ResultSrc,
    input logic RegWrite,
    input logic RamWrite,
    input logic [2:0] IMMsrc,

    output logic [WD-1:0] A0,
    output logic flag,
    output logic [WD-1:0] IMM,
    output logic [WD-1:0] DOutAlu
);

logic [WD-1:0] DOut1;
logic [WD-1:0] DOut2;
logic [WD-1:0] N2;
logic [WD-1:0] DInReg;
logic [WD-1:0] DOutRam;

logic op5;
logic func75;
logic [2:0] func3;
logic [2:0] ALUctrl;
logic [2:0] ALUflag;


assign func3 = instr[WD-18:WD-20];
assign op5 = instr[WD-31];
assign func75 = instr[WD-2];

always_comb begin
    if (ALUsrc) N2 = IMM;
    else N2 = DOut2;
end

always_comb 
case (ResultSrc)
    2'b00: DInReg = DOutAlu;
    2'b01: DInReg = DOutRam;
    2'b10: DInReg = PC+4;
    2'b11: DInReg = N2;
    default DInReg = DOutAlu;
endcase


reg32 R1(
    .AdIn(AdIn),
    .AdOut1(AdOut1),
    .AdOut2(AdOut2),
    .DIn(DInReg),
    .RegWrite(RegWrite),
    .clk(clk),

    .DOut1(DOut1),
    .DOut2(DOut2),
    .A0(A0)
);

alu A1(
    .ALUctrl(ALUctrl),
    .ALUflag(ALUflag),
    .N1(DOut1),
    .N2(N2),

    .flag(flag),
    .out(DOutAlu)
);

aludecode A11(
    .func3(func3),
    .op5(op5),
    .func75(func75),
    .ALUop(ALUop),

    .ALUctrl(ALUctrl)
);

aluflagdecode A12(
    .func3(func3),
    .ALUop(ALUop),

    .ALUflag(ALUflag)
);

imm I1(
    .IMMsrc(IMMsrc),
    .instr(instr),
    .out(IMM)
);

ram R2(
    .clk(clk),
    .DIn(DOut2),
    .Ad(DOutAlu),
    .RamWrite(RamWrite),
    .func3(func3),

    .DOut(DOutRam)
);

endmodule

single-cycle_RISC-V_model/main.sv
module main #(WA = 5, WD = 32)(
    input logic clk,
    input logic rst,
    output logic [WD-1:0] A0
);

logic [WD-1:0] instr;
logic [WD-1:0] IMMop;

logic [WA-1:0] AdIn;
logic [WA-1:0] AdOut1;
logic [WA-1:0] AdOut2;
logic [2:0] func3;

logic ALUsrc;
logic [1:0] ALUop;
logic RamWrite;
logic RegWrite;
logic [2:0] IMMsrc;
logic [1:0] ResultSrc;
logic [1:0] PCsrc;

logic [WD-1:0] PC;
logic [WD-1:0] DOutAlu;

logic flag;

assign AdIn = instr[WD-21:WD-25];
assign AdOut1 = instr[WD-13:WD-17];
assign AdOut2 = instr[WD-8:WD-12];

datapath1 D1(
    .clk(clk),

    .instr(instr),

    .AdIn(AdIn),
    .AdOut1(AdOut1),
    .AdOut2(AdOut2),
    .ALUsrc(ALUsrc),
    
    .ALUop(ALUop),
    .RamWrite(RamWrite),
    .RegWrite(RegWrite),
    .IMMsrc(IMMsrc),
    .ResultSrc(ResultSrc),

    .PC(PC),

    .IMM(IMMop),
    .flag(flag),
    .A0(A0),
    .DOutAlu(DOutAlu)
);

control C1(
    .instr(instr),
    .flag(flag),

    .RegWrite(RegWrite),
    .RamWrite(RamWrite),
    .ALUop(ALUop),
    .ALUsrc(ALUsrc),
    .IMMsrc(IMMsrc),
    .PCsrc(PCsrc),
    .ResultSrc(ResultSrc)
);

datapath2 D2(
    .clk(clk),
    .rst(rst),
    .PCsrc(PCsrc),
    .IMMop(IMMop),

    .instr(instr),
    .PC(PC),
    .DOutAlu(DOutAlu)
);

endmodule

single-cycle_RISC-V_model/main.vcd
$version Generated by VerilatedVcd $end
$timescale 1ps $end
 $scope module TOP $end
  $var wire 1 d clk $end
  $var wire 1 e rst $end
  $var wire 32 f A0 [31:0] $end
  $scope module main $end
   $var wire 32 g WA [31:0] $end
   $var wire 32 h WD [31:0] $end
   $var wire 1 d clk $end
   $var wire 1 e rst $end
   $var wire 32 f A0 [31:0] $end
   $var wire 32 # instr [31:0] $end
   $var wire 32 $ IMMop [31:0] $end
   $var wire 5 % AdIn [4:0] $end
   $var wire 5 & AdOut1 [4:0] $end
   $var wire 5 ' AdOut2 [4:0] $end
   $var wire 3 i func3 [2:0] $end
   $var wire 1 ( ALUsrc $end
   $var wire 2 ) ALUop [1:0] $end
   $var wire 1 * RamWrite $end
   $var wire 1 + RegWrite $end
   $var wire 3 , IMMsrc [2:0] $end
   $var wire 2 - ResultSrc [1:0] $end
   $var wire 2 . PCsrc [1:0] $end
   $var wire 32 / PC [31:0] $end
   $var wire 32 0 DOutAlu [31:0] $end
   $var wire 1 1 flag $end
   $scope module C1 $end
    $var wire 32 h W [31:0] $end
    $var wire 32 # instr [31:0] $end
    $var wire 1 1 flag $end
    $var wire 1 + RegWrite $end
    $var wire 1 * RamWrite $end
    $var wire 2 ) ALUop [1:0] $end
    $var wire 1 ( ALUsrc $end
    $var wire 3 , IMMsrc [2:0] $end
    $var wire 2 . PCsrc [1:0] $end
    $var wire 2 - ResultSrc [1:0] $end
    $var wire 7 2 op7 [6:0] $end
    $var wire 2 3 PCsrc_req1 [1:0] $end
   $upscope $end
   $scope module D1 $end
    $var wire 32 g WAD [31:0] $end
    $var wire 32 h WD [31:0] $end
    $var wire 1 d clk $end
    $var wire 5 % AdIn [4:0] $end
    $var wire 5 & AdOut1 [4:0] $end
    $var wire 5 ' AdOut2 [4:0] $end
    $var wire 32 # instr [31:0] $end
    $var wire 32 / PC [31:0] $end
    $var wire 1 ( ALUsrc $end
    $var wire 2 ) ALUop [1:0] $end
    $var wire 2 - ResultSrc [1:0] $end
    $var wire 1 + RegWrite $end
    $var wire 1 * RamWrite $end
    $var wire 3 , IMMsrc [2:0] $end
    $var wire 32 f A0 [31:0] $end
    $var wire 1 1 flag $end
    $var wire 32 $ IMM [31:0] $end
    $var wire 32 0 DOutAlu [31:0] $end
    $var wire 32 4 DOut1 [31:0] $end
    $var wire 32 5 DOut2 [31:0] $end
    $var wire 32 6 N2 [31:0] $end
    $var wire 32 7 DInReg [31:0] $end
    $var wire 32 8 DOutRam [31:0] $end
    $var wire 1 9 op5 $end
    $var wire 1 : func75 $end
    $var wire 3 ; func3 [2:0] $end
    $var wire 3 < ALUctrl [2:0] $end
    $var wire 3 = ALUflag [2:0] $end
    $scope module A1 $end
     $var wire 32 h W [31:0] $end
     $var wire 3 < ALUctrl [2:0] $end
     $var wire 3 = ALUflag [2:0] $end
     $var wire 32 4 N1 [31:0] $end
     $var wire 32 6 N2 [31:0] $end
     $var wire 32 0 out [31:0] $end
     $var wire 1 1 flag $end
    $upscope $end
    $scope module A11 $end
     $var wire 3 ; func3 [2:0] $end
     $var wire 2 ) ALUop [1:0] $end
     $var wire 1 : func75 $end
     $var wire 1 9 op5 $end
     $var wire 3 < ALUctrl [2:0] $end
    $upscope $end
    $scope module A12 $end
     $var wire 3 ; func3 [2:0] $end
     $var wire 2 ) ALUop [1:0] $end
     $var wire 3 = ALUflag [2:0] $end
    $upscope $end
    $scope module I1 $end
     $var wire 32 h W [31:0] $end
     $var wire 3 , IMMsrc [2:0] $end
     $var wire 32 # instr [31:0] $end
     $var wire 32 $ out [31:0] $end
     $var wire 1 > sign $end
    $upscope $end
    $scope module R1 $end
     $var wire 32 g WAD [31:0] $end
     $var wire 32 h WD [31:0] $end
     $var wire 32 j R0 [31:0] $end
     $var wire 1 d clk $end
     $var wire 1 + RegWrite $end
     $var wire 5 % AdIn [4:0] $end
     $var wire 5 & AdOut1 [4:0] $end
     $var wire 5 ' AdOut2 [4:0] $end
     $var wire 32 7 DIn [31:0] $end
     $var wire 32 4 DOut1 [31:0] $end
     $var wire 32 5 DOut2 [31:0] $end
     $var wire 32 f A0 [31:0] $end
     $var wire 32 ? RomArr[0] [31:0] $end
     $var wire 32 @ RomArr[1] [31:0] $end
     $var wire 32 A RomArr[2] [31:0] $end
     $var wire 32 B RomArr[3] [31:0] $end
     $var wire 32 C RomArr[4] [31:0] $end
     $var wire 32 D RomArr[5] [31:0] $end
     $var wire 32 E RomArr[6] [31:0] $end
     $var wire 32 F RomArr[7] [31:0] $end
     $var wire 32 G RomArr[8] [31:0] $end
     $var wire 32 H RomArr[9] [31:0] $end
     $var wire 32 I RomArr[10] [31:0] $end
     $var wire 32 J RomArr[11] [31:0] $end
     $var wire 32 K RomArr[12] [31:0] $end
     $var wire 32 L RomArr[13] [31:0] $end
     $var wire 32 M RomArr[14] [31:0] $end
     $var wire 32 N RomArr[15] [31:0] $end
     $var wire 32 O RomArr[16] [31:0] $end
     $var wire 32 P RomArr[17] [31:0] $end
     $var wire 32 Q RomArr[18] [31:0] $end
     $var wire 32 R RomArr[19] [31:0] $end
     $var wire 32 S RomArr[20] [31:0] $end
     $var wire 32 T RomArr[21] [31:0] $end
     $var wire 32 U RomArr[22] [31:0] $end
     $var wire 32 V RomArr[23] [31:0] $end
     $var wire 32 W RomArr[24] [31:0] $end
     $var wire 32 X RomArr[25] [31:0] $end
     $var wire 32 Y RomArr[26] [31:0] $end
     $var wire 32 Z RomArr[27] [31:0] $end
     $var wire 32 [ RomArr[28] [31:0] $end
     $var wire 32 \ RomArr[29] [31:0] $end
     $var wire 32 ] RomArr[30] [31:0] $end
     $var wire 32 ^ RomArr[31] [31:0] $end
    $upscope $end
    $scope module R2 $end
     $var wire 32 h WA [31:0] $end
     $var wire 32 k WAM [31:0] $end
     $var wire 32 l WB [31:0] $end
     $var wire 32 h WD [31:0] $end
     $var wire 1 d clk $end
     $var wire 32 0 Ad [31:0] $end
     $var wire 1 * RamWrite $end
     $var wire 3 ; func3 [2:0] $end
     $var wire 32 5 DIn [31:0] $end
     $var wire 32 8 DOut [31:0] $end
     $var wire 18 _ AdM [17:0] $end
     $var wire 32 ` show [31:0] $end
    $upscope $end
   $upscope $end
   $scope module D2 $end
    $var wire 32 h W [31:0] $end
    $var wire 1 d clk $end
    $var wire 1 e rst $end
    $var wire 2 . PCsrc [1:0] $end
    $var wire 32 $ IMMop [31:0] $end
    $var wire 32 0 DOutAlu [31:0] $end
    $var wire 32 / PC [31:0] $end
    $var wire 32 # instr [31:0] $end
    $var wire 32 a PCN [31:0] $end
    $var wire 32 b branch_pc [31:0] $end
    $scope module P1 $end
     $var wire 32 h W [31:0] $end
     $var wire 1 d clk $end
     $var wire 1 e rst $end
     $var wire 32 a PCN [31:0] $end
     $var wire 32 / PC [31:0] $end
    $upscope $end
    $scope module R1 $end
     $var wire 32 l WAD [31:0] $end
     $var wire 32 l WD [31:0] $end
     $var wire 8 c AddrIn [7:0] $end
     $var wire 32 # DOut [31:0] $end
    $upscope $end
   $upscope $end
  $upscope $end
 $upscope $end
$enddefinitions $end


#0
b00000000000000000000000000000000 #
b00000000000000000000000000000000 $
b00000 %
b00000 &
b00000 '
0(
b00 )
0*
0+
b000 ,
b00 -
b00 .
b00000000000000000000000000000000 /
b00000000000000000000000000000000 0
11
b0000000 2
b00 3
b00000000000000000000000000000000 4
b00000000000000000000000000000000 5
b00000000000000000000000000000000 6
b00000000000000000000000000000000 7
b00000000000000000000000000000000 8
09
0:
b000 ;
b000 <
b000 =
0>
b00000000000000000000000000000000 ?
b00000000000000000000000000000000 @
b00000000000000000000000000000000 A
b00000000000000000000000000000000 B
b00000000000000000000000000000000 C
b00000000000000000000000000000000 D
b00000000000000000000000000000000 E
b00000000000000000000000000000000 F
b00000000000000000000000000000000 G
b00000000000000000000000000000000 H
b00000000000000000000000000000000 I
b00000000000000000000000000000000 J
b00000000000000000000000000000000 K
b00000000000000000000000000000000 L
b00000000000000000000000000000000 M
b00000000000000000000000000000000 N
b00000000000000000000000000000000 O
b00000000000000000000000000000000 P
b00000000000000000000000000000000 Q
b00000000000000000000000000000000 R
b00000000000000000000000000000000 S
b00000000000000000000000000000000 T
b00000000000000000000000000000000 U
b00000000000000000000000000000000 V
b00000000000000000000000000000000 W
b00000000000000000000000000000000 X
b00000000000000000000000000000000 Y
b00000000000000000000000000000000 Z
b00000000000000000000000000000000 [
b00000000000000000000000000000000 \
b00000000000000000000000000000000 ]
b00000000000000000000000000000000 ^
b000000000000000000 _
b00000000000000000000000000000000 `
b00000000000000000000000000000100 a
b00000000000000000000000000000000 b
b00000000 c
0d
0e
b00000000000000000000000000000000 f
b00000000000000000000000000000101 g
b00000000000000000000000000100000 h
b000 i
b00000000000000000000000000001010 j
b00000000000000000000000000010010 k
b00000000000000000000000000001000 l
#1
b00000000000100000000010110010011 #
b00000000000000000000000000000001 $
b01011 %
b00001 '
1(
b10 )
1+
b00000000000000000000000000000001 0
01
b0010011 2
b00000000000000000000000000000001 6
b00000000000000000000000000000001 7
b00000000000000000000000000000010 8
19
b000000000000000001 _
b00010100000101010001011000010111 `
b00000000000000000000000000000001 b
1d
#2
0d
#3
b00000000000100000000011000010011 #
b01100 %
b00000000000000000000000000000100 /
b00000000000000000000000000000001 J
b00000000000000000000000000001000 a
b00000000000000000000000000000101 b
b00000100 c
1d
#4
0d
#5
b00000000011100000000011010010011 #
b00000000000000000000000000000111 $
b01101 %
b00111 '
b00000000000000000000000000001000 /
b00000000000000000000000000000111 0
b00000000000000000000000000000111 6
b00000000000000000000000000000111 7
b00000000000000000000000000001001 8
b00000000000000000000000000000001 K
b000000000000000111 _
b00000000000000000000000000001100 a
b00000000000000000000000000001111 b
b00001000 c
1d
#6
0d
#7
b00000000110101011001010110110011 #
b00000000000000000000000000001101 $
b01011 %
b01011 &
b01101 '
b00000000000000000000000000001100 /
b00000000000000000010000000000000 0
11
b0110011 2
b00000000000000000000000000000001 4
b00000000000000000000000000000111 5
b00000000000000000000000000001101 6
b00000000000000000010000000000000 7
b11111111111111111001001110010010 8
b001 ;
b110 <
b001 =
b00000000000000000000000000000111 L
b000010000000000000 _
b00000000000000000000000000010000 a
b00000000000000000000000000011001 b
b00001100 c
1d
#8
0d
#9
b00000000110001011101010110110011 #
b00000000000000000000000000001100 $
b01100 '
b00000000000000000000000000010000 /
b00000000000000000000000000000010 0
01
b00000000000000000010000000000000 4
b00000000000000000000000000000001 5
b00000000000000000000000000001100 6
b00000000000000000000000000000010 7
b00000000000000000000001100000100 8
b101 ;
b111 <
b100 =
b00000000000000000010000000000000 J
b000000000000000010 _
b00000000000000000000000000010100 a
b00000000000000000000000000011100 b
b00010000 c
1d
#10
0d
#11
b00000000110001011000010110110011 #
b00000000000000000000000000010100 /
b00000000000000000000000000001110 0
b00000000000000000000000000000010 4
b00000000000000000000000000001110 7
b00000000000000000000000000010001 8
b000 ;
b000 <
b000 =
b00000000000000000000000000000010 J
b000000000000001110 _
b00000000000000000000000000011000 a
b00000000000000000000000000100000 b
b00010100 c
1d
#12
0d
#13
b01000000110101011000010110110011 #
b00000000000000000000010000001101 $
b01101 '
b00000000000000000000000000011000 /
b11111111111111111111110000000001 0
b00000000000000000000000000001110 4
b00000000000000000000000000000111 5
b00000000000000000000010000001101 6
b11111111111111111111110000000001 7
b00000000000000000000000000000000 8
1:
b001 <
b00000000000000000000000000001110 J
b111111110000000001 _
b00000000000000000000000000011100 a
b00000000000000000000010000100101 b
b00011000 c
1d
#14
0d
#15
b00000000110001011110010110110011 #
b00000000000000000000000000001100 $
b01100 '
b00000000000000000000000000011100 /
b11111111111111111111110000001101 0
11
b11111111111111111111110000000001 4
b00000000000000000000000000000001 5
b00000000000000000000000000001100 6
b11111111111111111111110000001101 7
0:
b110 ;
b011 <
b111 =
b11111111111111111111110000000001 J
b111111110000001101 _
b00000000000000000000000000100000 a
b00000000000000000000000000101000 b
b00011100 c
1d
#16
0d
#17
b00000000110101011111010110110011 #
b00000000000000000000000000001101 $
b01101 '
b00000000000000000000000000100000 /
b00000000000000000000000000001101 0
b11111111111111111111110000001101 4
b00000000000000000000000000000111 5
b00000000000000000000000000001101 6
b00000000000000000000000000001101 7
b00010000000100010001001000010100 8
b111 ;
b010 <
b011 =
b11111111111111111111110000001101 J
b000000000000001101 _
b00000000000000000000000000100100 a
b00000000000000000000000000101101 b
b00100000 c
1d
#18
0d
#19
b00000000010100000000010110010011 #
b00000000000000000000000000000101 $
b00000 &
b00101 '
b00000000000000000000000000100100 /
b00000000000000000000000000000101 0
01
b0010011 2
b00000000000000000000000000000000 4
b00000000000000000000000000000000 5
b00000000000000000000000000000101 6
b00000000000000000000000000000101 7
b00000000000000000000000000000111 8
b000 ;
b000 <
b000 =
b00000000000000000000000000001101 J
b000000000000000101 _
b00000000000000000000000000101000 a
b00000000000000000000000000101001 b
b00100100 c
1d
#20
0d
