single-cycle_RISC-V_model/rom.sv
module rom #(parameter WAD = 16, WD = 8)(
    input logic [WAD-1: 0] AddrIn,
    output logic [WD*4-1: 0] DOut
);

logic [WD-1: 0] RomArr [2**WAD-1: 0]; // too large to simulate 2**32 rom so using 2*16

initial begin
    $readmemh("asm4.mem", RomArr);
end;

assign DOut = {RomArr[AddrIn], RomArr[AddrIn+1], RomArr[AddrIn+2], RomArr[AddrIn+3]};

/*
Already successfully tested program

from project brief:
asm1.mem, solution: 0xFE (254)
asm2.mem, solution: 0x3E8 (1000)
asm3.mem, solution: 0x12C (300)
asm4.mem, solution: 0x35 (53)
asm5.mem, solution: 0x3C03 (15363) (note this needs about 300000 cycles in testbench)

self written:
rom1.mem (only addi and bne)
rom2.mem (many other instructions)

Undertest program
...

 */

endmodule

single_cycle-RISC-V/PCReg.sv
module PCReg #(parameter W = 32)(
    input logic clk,
    input logic rst,
    input logic [W-1: 0] PCN,
    output logic [W-1: 0] PC
);

always_ff@(posedge clk)
    if (rst) PC <= {W{1'b0}};
    else PC <= PCN;

endmodule

single-cycle_RISC-V_model/datapath2.sv
module datapath2 #(parameter W = 32)(
    input logic clk,
    input logic rst,
    input logic [1:0] PCsrc,
    input logic [W-1:0] IMM,
    input logic [W-1:0] DOutAlu,

    output logic [W-1:0] PC,
    output logic [W-1:0] instr
);

logic [W-1:0] PCN;

always_comb 
    case (PCsrc)
        2'b00: PCN = PC + 4;
        2'b01: PCN = PC + IMM;
        2'b11: PCN = DOutAlu;
        default: PCN = PC + 4;
    endcase

pcreg P1(
    .clk(clk),
    .rst(rst),
    .PCN(PCN),

    .PC(PC)
);

rom R1(
    .AddrIn(PC),

    .DOut(instr)
);


endmodule

single-cycle_RISC-V_model/control.sv
module control #(parameter W = 32)(
    input logic [W-1:0] instr,
    input logic flag,
    output logic RegWrite,
    output logic RamWrite,
    output logic [1:0] ALUop,
    output logic ALUsrc,
    output logic [2:0] IMMsrc,
    output logic [1:0] PCsrc,
    output logic [1:0] ResultSrc
);

/*
name    parameter       |   op      func3   func7       explanation

Already tested instructions:

addi    Rd, Ra, IMM12   |   0010011 000     x
slli    Rd, Ra, IMM12   |   0010011 001     x
slti    Rd, Ra, IMM12   |   0010011 010     x
xori    Rd, Ra, IMM12   |   0010011 100     x
srli    Rd, Ra, IMM12   |   0010011 101     x
ori     Rd, Ra, IMM12   |   0010011 110     x
andi    Rd, Ra, IMM12   |   0010011 111     x

add     Rd, Ra, Rb      |   0110011 000     0000000 
sub     Rd, Ra, Rb      |   0110011 000     0100000
sll     Rd, Ra, Rb      |   0110011 001     0000000     logic shift left
slt     Rd, Ra, Rb      |   0110011 010     0000000     set less than
xor     Rd, Ra, Rb      |   0110011 100     0000000
srl     Rd, Ra, Rb      |   0110011 101     0000000     logic shift right
or      Rd, Ra, Rb      |   0110011 110     0000000
and     Rd, Ra, Rb      |   0110011 111     0000000

lui     Rd, IMM20       |   0110111 x       x

bne     Rd, Ra, IMM     |   1100011 001     x
beq     Rd, Ra, IMM     |   1100011 000     x
blt     Rd, Ra, IMM     |   1100011 100     x
bge     Rd, Ra, IMM     |   1100011 101     x
bltu    Rd, Ra, IMM     |   1100011 110     x
bgeu    Rd, Ra, IMM     |   1100011 111     x

sb      Rb, IMM12(Ra)   |   0100011 000     x
sh      Rb, IMM12(Ra)   |   0000011 001     x
sw      Rb, IMM12(Ra)   |   0100011 010     x

lb      Rd, IMM12(Ra)   |   0000011 000     x
lh      Rd, IMM12(Ra)   |   0000011 001     x
lw      Rd, IMM12(Ra)   |   0000011 010     x
lbu     Rd, IMM12(Ra)   |   0000011 100     x
lhu     Rd, IMM12(Ra)   |   0000011 101     x

jal     Rd, IMM20       |   1101111 x       x
jalr    Rd, Ra, IMM12   |   1100111 000     x           actually belongs to i-type

under-testing instructions:

sltu    Rd, Ra, Rb      |   0110011 011     0000000     
sra     Rd, Ra, Rb      |   0110011 101     0100000     arithmetic shift left
auipc   Rd, IMM         |   

*/

logic [6:0] op7;

logic [1:0] PCsrc_req1;

always_comb begin
    op7 = instr[W-26:W-32];


    // IMMsrc to datapath1/imm
    case (op7)
        7'b0010011: IMMsrc = 3'b000; // i-type
        7'b0000011: IMMsrc = 3'b000; 
        7'b0011011: IMMsrc = 3'b000;
        7'b1100111: IMMsrc = 3'b000; // jalr

        7'b0100011: IMMsrc = 3'b001; // s-type

        7'b1100011: IMMsrc = 3'b010; // b-type

        7'b0110111: IMMsrc = 3'b011; // u-type
        7'b0010111: IMMsrc = 3'b011; // auipc

        
        7'b1101111: IMMsrc = 3'b100; // j-type

        default: IMMsrc = 3'b000;
    endcase


    // ALUop to datapath1/alu
    case (op7)
        7'b0100011: ALUop = 2'b00; // s-type
        7'b0000011: ALUop = 2'b00; // load

        7'b1100011: ALUop = 2'b01; // b-type

        7'b0010011: ALUop = 2'b10; // i-type
        
        7'b0110011: ALUop = 2'b10; // r-type

        7'b1101111: ALUop = 2'b11; // j-type
        7'b1100111: ALUop = 2'b11; // jalr
        7'b0010111: ALUop = 2'b11; // auipc

        default: ALUop = 2'b00;
    endcase


    // RegWrite to datapath1/reg32
    case (op7)
        7'b0110011: RegWrite = 1'b1; // r-type
        7'b0010011: RegWrite = 1'b1; // i-type
        7'b0011011: RegWrite = 1'b1;
        7'b0000011: RegWrite = 1'b1;
        7'b0110111: RegWrite = 1'b1; // u-type
        7'b0010111: RegWrite = 1'b1;
        7'b1100111: RegWrite = 1'b1; // jalr
        7'b1101111: RegWrite = 1'b1; // j-type
        default: RegWrite = 1'b0;
    endcase


    // RamWrite to datapath1/ram
    case (op7)
        7'b0100011: RamWrite = 1'b1; // s-type
        default: RamWrite = 1'b0;
    endcase


    // ALUsrc to datapath1
    case (op7)
        7'b0100011: ALUsrc = 1'b1; // s-type
        7'b0010011: ALUsrc = 1'b1; // i-type
        7'b0000011: ALUsrc = 1'b1; 
        7'b1100111: ALUsrc = 1'b1; // jalr
        7'b0110111: ALUsrc = 1'b1; // u-type
        7'b0011011: ALUsrc = 1'b1; // unsigned
        default: ALUsrc = 1'b0;
    endcase


    // ResultSrc to datapath1
    case (op7)
        7'b0000011: ResultSrc = 2'b01; // load
        7'b1101111: ResultSrc = 2'b10; // j-type
        7'b0110111: ResultSrc = 2'b11; // u-type
        default: ResultSrc = 2'b00;
    endcase


    // PCsrc to datapath2
    case (op7)
        7'b1100011: PCsrc_req1 = 2'b01; // b-type
        7'b1101111: PCsrc_req1 = 2'b01; // j-type
        7'b0010111: PCsrc_req1 = 2'b11; // auipc
        7'b1100111: PCsrc_req1 = 2'b11; // jalr
        default: PCsrc_req1 = 2'b00;
    endcase

    PCsrc = {PCsrc_req1[1], {PCsrc_req1[0] && flag}};
end

endmodule

single-cycle_RISC-V_model/ram.sv
module ram #(parameter WA = 32, WAM = 18, WB = 8, WD = 32)(
    input logic clk,
    input logic [WA-1:0] Ad,
    input logic RamWrite,
    input logic [2:0] func3,
    input logic [WD-1:0] DIn,
    output logic [WD-1:0] DOut
);
                 
logic [WB-1:0] RamArray [2**WAM-1:0]; // stored in byte
logic [WAM-1:0] AdM; // reduced in size, 2**32 is too large to simulate

logic [WD-1:0] show; // used for testing

initial begin
    $readmemh("triangle.mem", RamArray);
end;

always_comb begin 
    AdM = Ad[WAM-1:0];
    case (func3) 
        3'b000: DOut = {{24{RamArray[AdM][WB-1]}},RamArray[AdM]}; // lb
        3'b001: DOut = {{16{RamArray[AdM][WB-1]}},RamArray[AdM], RamArray[AdM+1]}; // lh
        3'b010: DOut = {RamArray[AdM], RamArray[AdM+1], RamArray[AdM+2], RamArray[AdM+3]}; // lw
        3'b100: DOut = {{24'b0},RamArray[AdM]}; // lbu
        3'b101: DOut = {{16'b0},RamArray[AdM], RamArray[AdM+1]}; // lhu
        default: DOut = {RamArray[AdM], RamArray[AdM+1], RamArray[AdM+2], RamArray[AdM+3]}; // lw
    endcase
end

always_ff@(posedge clk)
    if (RamWrite) 
    begin
        if (func3[1:0] == 2'b10)
        begin
            RamArray[AdM] <= DIn[WD-1:WD-8];
            RamArray[AdM+1] <= DIn[WD-9:WD-16];
            RamArray[AdM+2] <= DIn[WD-17:WD-24];
            RamArray[AdM+3] <= DIn[WD-25:0];
        end
        else if (func3[1:0] == 2'b01)
        begin
            RamArray[AdM] <= DIn[WD-17:WD-24];
            RamArray[AdM+1] <= DIn[WD-25:0];
        end
        else if (func3[1:0] == 2'b00) RamArray[AdM] <= DIn[WD-25:0];
    end

assign show = {RamArray[16], RamArray[17], RamArray[18], RamArray[19]};

endmodule

single-cycle_RISC-V_model/imm.sv
module imm #(parameter W = 32)(
    input logic [2:0] IMMsrc,
    input logic [W-1:0] instr,
    output logic [W-1:0] out
);

logic sign; // for 2's complement

assign sign = instr[W-1]; // not required by extend (U / J type)

always_comb case(IMMsrc)
    3'b000: out = {{20{sign}}, instr[W-1:W-12]}; // I-type
    3'b001: out = {{20{sign}}, instr[W-1:W-7], instr[W-21:W-25]}; // S-type
    3'b010: out = {{19{sign}}, instr[W-1], instr[W-25], instr[W-2:W-7], instr[W-21:W-24], 1'b0}; //B-type
    3'b011: out = {instr[W-1:W-20], 12'b0}; // U-type
    3'b100: out = {{11{sign}}, instr[W-1], instr[W-13:W-20], instr[W-12], instr[W-2:W-11], 1'b0}; // J-type
    default: out = {{20{sign}}, instr[W-1:W-12]}; // I-type
endcase

endmodule

single-cycle_RISC-V_model/aludecode.sv
module aludecode (
    input logic [2:0] func3,
    input logic [1:0] ALUop,
    input logic func75,
    input logic op5,
    output logic [3:0] ALUctrl // first bit: whether using flag operation ? 1 : 0
);

always_comb begin 
    case ({ALUop, func3})
        5'b10111: ALUctrl = 4'b0010; // and
        5'b10110: ALUctrl = 4'b0011; // or
        5'b10100: ALUctrl = 4'b0100; // xor
        5'b10001: ALUctrl = 4'b0101; // sll

        // ----- with ALUcrtl[3] = 1, we have flag related operations -----

        5'b10010: ALUctrl = 4'b1100; // slt (based on blt)
        5'b10011: ALUctrl = 4'b1110; // sltu (based on bltu)

        5'b01000: ALUctrl = 4'b1000; // beq
        5'b01001: ALUctrl = 4'b1001; // bne
        //as ALUctrl misses 4'b1010, we set a useless "flag = 0" in alu
        5'b01100: ALUctrl = 4'b1100; // blt
        5'b01101: ALUctrl = 4'b1101; // bge
        5'b01110: ALUctrl = 4'b1110; // bltu
        5'b01111: ALUctrl = 4'b1111; // bgeu

        default: ALUctrl = 4'b0000;  
    endcase

    case ({func3, op5, func75})
        5'b00011: ALUctrl = 4'b0001; // sub
        5'b00000: ALUctrl = 4'b0000; // add
        5'b00001: ALUctrl = 4'b0000; // add
        5'b00010: ALUctrl = 4'b0000; // add
        default: ALUctrl = ALUctrl;
    endcase

    case ({ALUop, func3, func75})
        6'b101010: ALUctrl = 4'b0110; // srl
        6'b101011: ALUctrl = 4'b0111; // sra
        default: ALUctrl = ALUctrl;
    endcase

    case (ALUop)
        2'b00: ALUctrl = 4'b0000; // add (used in save, load)
        2'b11: ALUctrl = 4'b1011; // flag = 1 (used in jal, jalr, auipc)
        default: ALUctrl = ALUctrl;
    endcase
end
    
endmodule

single-cycle_RISC-V_model/alu.sv
module alu #(parameter W = 32)(
    input logic [3: 0] ALUctrl,
    input logic [W-1: 0] N1,
    input logic [W-1: 0] N2,
    output logic [W-1: 0] out,
    output logic flag
);

logic flagZ; // zero
logic flagC; // carry
logic flagS; // sign
logic flagV; // overflow

always_comb begin
    casez (ALUctrl)
        4'b1???: {flagC, out} = {1'b0, N1} + {1'b0, ~N2+1}; // used in flag operation and slt / sltu (depend by aluflag)
        4'b0000: out = N1 + N2; // add
        4'b0001: out = N1 - N2; // sub
        4'b0010: out = N1 & N2; // and
        4'b0011: out = N1 | N2; // or
        4'b0100: out = N1 ^ N2; // xor
        4'b0101: out = N1 << N2;  // sll
        4'b0110: out = N1 >> N2;  // srl
        4'b0111: out = N1 >> N2;  // srl

        default out = N1 + N2;
    endcase

    flagS = out[W-1];

    if (out == 0) flagZ = 1'b1;
    else flagZ = 1'b0;

    if ((N1[W-1] == 0 && N2[W-1] == 1 && out < 0) || (N1[W-1] == 1 && N2[W-1] == 0 && out >= 0)) flagV = 1'b1;
    else flagV = 1'b0;

    case (ALUctrl)
        4'b1000: flag = flagZ; // beq
        4'b1001: flag = ~flagZ; // bne
        4'b1010: flag = 1'b0;
        4'b1011: flag = 1'b1; // jal, jalr, auipc
        4'b1100: flag = (flagS != flagV); // blt, slt
        4'b1101: flag = (flagS == flagV); // bge
        4'b1110: flag = ~flagC; // bltu, sltu
        4'b1111: flag = flagC; // bgeu

        default flag = 0;
    endcase

    if (ALUctrl == 4'b1100 || ALUctrl == 4'b1110) out = {{W-1{1'b0}}, flag};
end

endmodule

single-cycle_RISC-V_model/reg32.sv
module reg32 #(parameter WAD = 5, WD = 32, R0 = 10)( // A0 = reg[10] or reg 01010
    input logic clk,
    input logic RegWrite,
    input logic [WAD-1:0] AdIn,
    input logic [WAD-1:0] AdOut1,
    input logic [WAD-1:0] AdOut2,
    output logic [WD-1:0] DIn,
    output logic [WD-1:0] DOut1,
    output logic [WD-1:0] DOut2,
    output logic [WD-1:0] A0
);

logic [WD-1: 0] RegArr [2**WAD-1: 0];

always_ff@(posedge clk)
begin
    if (RegWrite) RegArr[AdIn] <= DIn;

    RegArr[0] <= 32'b0;
end

assign DOut1 = RegArr[AdOut1];
assign DOut2 = RegArr[AdOut2];

assign A0 = RegArr[R0];

endmodule

/* 
x0  	zero	Always zero	
x1      ra	    Return address	
x2	    sp	    Stack pointer
x3	    gp	    Global pointer	
x4	    tp	    Thread pointer	
x5	    t0	    Temporary / alternate return address
x6–7	t1–2	Temporaries
x8	    s0/fp	Saved register / frame pointer
x9	    s1	    Saved register
x10–11	a0–1	Function arguments / return values
x12–17	a2–7	Function arguments
x18–27	s2–11	Saved registers
x28–31	t3–6	Temporaries

32 floating-point extension registers

f0–7	ft0–7	Floating-point temporaries
f8–9	fs0–1	Floating-point saved registers
f10–11	fa0–1	Floating-point arguments/return values
f12–17	fa2–7	Floating-point arguments
f18–27	fs2–11	Floating-point saved registers
f28–31	ft8–11	Floating-point temporaries
*/

single-cycle_RISC-V_model/datapath1.sv
module datapath1 #(parameter WAD = 5, WD = 32)(
    input logic clk,

    input logic [WD-1:0] instr,
    input logic [WD-1:0] PC,

    input logic ALUsrc,
    input logic [1:0] ALUop,
    input logic [1:0] ResultSrc,
    input logic RegWrite,
    input logic RamWrite,
    input logic [2:0] IMMsrc,

    output logic [WD-1:0] A0,
    output logic flag,
    output logic [WD-1:0] IMM,
    output logic [WD-1:0] DOutAlu
);

logic [WD-1:0] DOut1;
logic [WD-1:0] DOut2;
logic [WD-1:0] N2;
logic [WD-1:0] DInReg;
logic [WD-1:0] DOutRam;

logic [3:0] ALUctrl;

logic [WAD-1:0] AdIn;
logic [WAD-1:0] AdOut1;
logic [WAD-1:0] AdOut2;
logic [2:0] func3;
logic op5;
logic func75;
assign AdIn = instr[WD-21:WD-25];
assign AdOut1 = instr[WD-13:WD-17];
assign AdOut2 = instr[WD-8:WD-12];
assign func3 = instr[WD-18:WD-20];
assign op5 = instr[WD-27];
assign func75 = instr[WD-2];


always_comb begin
    if (ALUsrc) N2 = IMM;
    else N2 = DOut2;

    case (ResultSrc)
        2'b00: DInReg = DOutAlu;
        2'b01: DInReg = DOutRam;
        2'b10: DInReg = PC+4;
        2'b11: DInReg = N2;
        default DInReg = DOutAlu;
    endcase 
end


reg32 R1(
    .AdIn(AdIn),
    .AdOut1(AdOut1),
    .AdOut2(AdOut2),
    .DIn(DInReg),
    .RegWrite(RegWrite),
    .clk(clk),

    .DOut1(DOut1),
    .DOut2(DOut2),
    .A0(A0)
);

alu A1(
    .ALUctrl(ALUctrl),
    .N1(DOut1),
    .N2(N2),

    .flag(flag),
    .out(DOutAlu)
);

aludecode A11(
    .func3(func3),
    .op5(op5),
    .func75(func75),
    .ALUop(ALUop),

    .ALUctrl(ALUctrl)
);

imm I1(
    .IMMsrc(IMMsrc),
    .instr(instr),
    .out(IMM)
);

ram R2(
    .clk(clk),
    .DIn(DOut2),
    .Ad(DOutAlu),
    .RamWrite(RamWrite),
    .func3(func3),

    .DOut(DOutRam)
);

endmodule

single-cycle_RISC-V_model/main.sv
module main #(WA = 5, WD = 32)(
    input logic clk,
    input logic rst,
    output logic [WD-1:0] A0
);

// data transfer
logic [WD-1:0] instr;
logic [WD-1:0] IMM;
logic [WD-1:0] PC;
logic [WD-1:0] DOutAlu;

// control signals
logic ALUsrc;
logic [1:0] ALUop;
logic RamWrite;
logic RegWrite;
logic [2:0] IMMsrc;
logic [1:0] ResultSrc;
logic [1:0] PCsrc;

logic flag;


datapath1 D1(
    .clk(clk),

    // input data
    .PC(PC),
    .instr(instr),

    // input control signals
    .ALUsrc(ALUsrc),
    .ALUop(ALUop),
    .RamWrite(RamWrite),
    .RegWrite(RegWrite),
    .IMMsrc(IMMsrc),
    .ResultSrc(ResultSrc),

    // output
    .IMM(IMM),
    .flag(flag),
    .A0(A0),
    .DOutAlu(DOutAlu)
);

control C1(
    .instr(instr),
    .flag(flag),

    .RegWrite(RegWrite),
    .RamWrite(RamWrite),
    .ALUop(ALUop),
    .ALUsrc(ALUsrc),
    .IMMsrc(IMMsrc),
    .PCsrc(PCsrc),
    .ResultSrc(ResultSrc)
);

datapath2 D2(
    .clk(clk),
    .rst(rst),
    .PCsrc(PCsrc),
    .IMM(IMM),

    .instr(instr),
    .PC(PC),
    .DOutAlu(DOutAlu)
);

endmodule

single-cycle_RISC-V_model/main.vcd
$version Generated by VerilatedVcd $end
$timescale 1ps $end
 $scope module TOP $end
  $var wire 1 c clk $end
  $var wire 1 d rst $end
  $var wire 32 e A0 [31:0] $end
  $scope module main $end
   $var wire 32 i WA [31:0] $end
   $var wire 32 j WD [31:0] $end
   $var wire 1 c clk $end
   $var wire 1 d rst $end
   $var wire 32 e A0 [31:0] $end
   $var wire 32 6 instr [31:0] $end
   $var wire 32 # IMM [31:0] $end
   $var wire 32 7 PC [31:0] $end
   $var wire 32 . DOutAlu [31:0] $end
   $var wire 1 $ ALUsrc $end
   $var wire 2 % ALUop [1:0] $end
   $var wire 1 & RamWrite $end
   $var wire 1 ' RegWrite $end
   $var wire 3 ( IMMsrc [2:0] $end
   $var wire 2 ) ResultSrc [1:0] $end
   $var wire 2 * PCsrc [1:0] $end
   $var wire 1 / flag $end
   $scope module C1 $end
    $var wire 32 j W [31:0] $end
    $var wire 32 6 instr [31:0] $end
    $var wire 1 / flag $end
    $var wire 1 ' RegWrite $end
    $var wire 1 & RamWrite $end
    $var wire 2 % ALUop [1:0] $end
    $var wire 1 $ ALUsrc $end
    $var wire 3 ( IMMsrc [2:0] $end
    $var wire 2 * PCsrc [1:0] $end
    $var wire 2 ) ResultSrc [1:0] $end
    $var wire 7 + op7 [6:0] $end
    $var wire 2 , PCsrc_req1 [1:0] $end
   $upscope $end
   $scope module D1 $end
    $var wire 32 i WAD [31:0] $end
    $var wire 32 j WD [31:0] $end
    $var wire 1 c clk $end
    $var wire 32 6 instr [31:0] $end
    $var wire 32 7 PC [31:0] $end
    $var wire 1 $ ALUsrc $end
    $var wire 2 % ALUop [1:0] $end
    $var wire 2 ) ResultSrc [1:0] $end
    $var wire 1 ' RegWrite $end
    $var wire 1 & RamWrite $end
    $var wire 3 ( IMMsrc [2:0] $end
    $var wire 32 e A0 [31:0] $end
    $var wire 1 / flag $end
    $var wire 32 # IMM [31:0] $end
    $var wire 32 . DOutAlu [31:0] $end
    $var wire 32 8 DOut1 [31:0] $end
    $var wire 32 9 DOut2 [31:0] $end
    $var wire 32 0 N2 [31:0] $end
    $var wire 32 1 DInReg [31:0] $end
    $var wire 32 f DOutRam [31:0] $end
    $var wire 4 - ALUctrl [3:0] $end
    $var wire 5 : AdIn [4:0] $end
    $var wire 5 ; AdOut1 [4:0] $end
    $var wire 5 < AdOut2 [4:0] $end
    $var wire 3 = func3 [2:0] $end
    $var wire 1 > op5 $end
    $var wire 1 ? func75 $end
    $scope module A1 $end
     $var wire 32 j W [31:0] $end
     $var wire 4 - ALUctrl [3:0] $end
     $var wire 32 8 N1 [31:0] $end
     $var wire 32 0 N2 [31:0] $end
     $var wire 32 . out [31:0] $end
     $var wire 1 / flag $end
     $var wire 1 2 flagZ $end
     $var wire 1 3 flagC $end
     $var wire 1 4 flagS $end
     $var wire 1 5 flagV $end
    $upscope $end
    $scope module A11 $end
     $var wire 3 = func3 [2:0] $end
     $var wire 2 % ALUop [1:0] $end
     $var wire 1 ? func75 $end
     $var wire 1 > op5 $end
     $var wire 4 - ALUctrl [3:0] $end
    $upscope $end
    $scope module I1 $end
     $var wire 32 j W [31:0] $end
     $var wire 3 ( IMMsrc [2:0] $end
     $var wire 32 6 instr [31:0] $end
     $var wire 32 # out [31:0] $end
     $var wire 1 @ sign $end
    $upscope $end
    $scope module R1 $end
     $var wire 32 i WAD [31:0] $end
     $var wire 32 j WD [31:0] $end
     $var wire 32 k R0 [31:0] $end
     $var wire 1 c clk $end
     $var wire 1 ' RegWrite $end
     $var wire 5 : AdIn [4:0] $end
     $var wire 5 ; AdOut1 [4:0] $end
     $var wire 5 < AdOut2 [4:0] $end
     $var wire 32 1 DIn [31:0] $end
     $var wire 32 8 DOut1 [31:0] $end
     $var wire 32 9 DOut2 [31:0] $end
     $var wire 32 e A0 [31:0] $end
     $var wire 32 A RegArr[0] [31:0] $end
     $var wire 32 B RegArr[1] [31:0] $end
     $var wire 32 C RegArr[2] [31:0] $end
     $var wire 32 D RegArr[3] [31:0] $end
     $var wire 32 E RegArr[4] [31:0] $end
     $var wire 32 F RegArr[5] [31:0] $end
     $var wire 32 G RegArr[6] [31:0] $end
     $var wire 32 H RegArr[7] [31:0] $end
     $var wire 32 I RegArr[8] [31:0] $end
     $var wire 32 J RegArr[9] [31:0] $end
     $var wire 32 K RegArr[10] [31:0] $end
     $var wire 32 L RegArr[11] [31:0] $end
     $var wire 32 M RegArr[12] [31:0] $end
     $var wire 32 N RegArr[13] [31:0] $end
     $var wire 32 O RegArr[14] [31:0] $end
     $var wire 32 P RegArr[15] [31:0] $end
     $var wire 32 Q RegArr[16] [31:0] $end
     $var wire 32 R RegArr[17] [31:0] $end
     $var wire 32 S RegArr[18] [31:0] $end
     $var wire 32 T RegArr[19] [31:0] $end
     $var wire 32 U RegArr[20] [31:0] $end
     $var wire 32 V RegArr[21] [31:0] $end
     $var wire 32 W RegArr[22] [31:0] $end
     $var wire 32 X RegArr[23] [31:0] $end
     $var wire 32 Y RegArr[24] [31:0] $end
     $var wire 32 Z RegArr[25] [31:0] $end
     $var wire 32 [ RegArr[26] [31:0] $end
     $var wire 32 \ RegArr[27] [31:0] $end
     $var wire 32 ] RegArr[28] [31:0] $end
     $var wire 32 ^ RegArr[29] [31:0] $end
     $var wire 32 _ RegArr[30] [31:0] $end
     $var wire 32 ` RegArr[31] [31:0] $end
    $upscope $end
    $scope module R2 $end
     $var wire 32 j WA [31:0] $end
     $var wire 32 l WAM [31:0] $end
     $var wire 32 m WB [31:0] $end
     $var wire 32 j WD [31:0] $end
     $var wire 1 c clk $end
     $var wire 32 . Ad [31:0] $end
     $var wire 1 & RamWrite $end
     $var wire 3 = func3 [2:0] $end
     $var wire 32 9 DIn [31:0] $end
     $var wire 32 f DOut [31:0] $end
     $var wire 20 g AdM [19:0] $end
     $var wire 32 a show [31:0] $end
    $upscope $end
   $upscope $end
   $scope module D2 $end
    $var wire 32 j W [31:0] $end
    $var wire 1 c clk $end
    $var wire 1 d rst $end
    $var wire 2 * PCsrc [1:0] $end
    $var wire 32 # IMM [31:0] $end
    $var wire 32 . DOutAlu [31:0] $end
    $var wire 32 7 PC [31:0] $end
    $var wire 32 6 instr [31:0] $end
    $var wire 32 h PCN [31:0] $end
    $scope module P1 $end
     $var wire 32 j W [31:0] $end
     $var wire 1 c clk $end
     $var wire 1 d rst $end
     $var wire 32 h PCN [31:0] $end
     $var wire 32 7 PC [31:0] $end
    $upscope $end
    $scope module R1 $end
     $var wire 32 n WAD [31:0] $end
     $var wire 32 m WD [31:0] $end
     $var wire 16 b AddrIn [15:0] $end
     $var wire 32 6 DOut [31:0] $end
    $upscope $end
   $upscope $end
  $upscope $end
 $upscope $end
$enddefinitions $end


#0
b00000000000000000000000000000000 #
0$
b00 %
0&
0'
b000 (
b00 )
b00 *
b0000000 +
b00 ,
b0000 -
b00000000000000000000000000000000 .
0/
b00000000000000000000000000000000 0
b00000000000000000000000000000000 1
02
03
04
05
b00000000000000000000000000000000 6
b00000000000000000000000000000000 7
b00000000000000000000000000000000 8
b00000000000000000000000000000000 9
b00000 :
b00000 ;
b00000 <
b000 =
0>
0?
0@
b00000000000000000000000000000000 A
b00000000000000000000000000000000 B
b00000000000000000000000000000000 C
b00000000000000000000000000000000 D
b00000000000000000000000000000000 E
b00000000000000000000000000000000 F
b00000000000000000000000000000000 G
b00000000000000000000000000000000 H
b00000000000000000000000000000000 I
b00000000000000000000000000000000 J
b00000000000000000000000000000000 K
b00000000000000000000000000000000 L
b00000000000000000000000000000000 M
b00000000000000000000000000000000 N
b00000000000000000000000000000000 O
b00000000000000000000000000000000 P
b00000000000000000000000000000000 Q
b00000000000000000000000000000000 R
b00000000000000000000000000000000 S
b00000000000000000000000000000000 T
b00000000000000000000000000000000 U
b00000000000000000000000000000000 V
b00000000000000000000000000000000 W
b00000000000000000000000000000000 X
b00000000000000000000000000000000 Y
b00000000000000000000000000000000 Z
b00000000000000000000000000000000 [
b00000000000000000000000000000000 \
b00000000000000000000000000000000 ]
b00000000000000000000000000000000 ^
b00000000000000000000000000000000 _
b00000000000000000000000000000000 `
b00000000000000000000000000000000 a
b0000000000000000 b
0c
0d
b00000000000000000000000000000000 e
b00000000000000000000000000000000 f
b00000000000000000000 g
b00000000000000000000000000000100 h
b00000000000000000000000000000101 i
b00000000000000000000000000100000 j
b00000000000000000000000000001010 k
b00000000000000000000000000010100 l
b00000000000000000000000000001000 m
b00000000000000000000000000010000 n
#1
b00000000000000000000000000110010 #
1$
b10 %
1'
b0010011 +
b00000000000000000000000000110010 .
b00000000000000000000000000110010 0
b00000000000000000000000000110010 1
b00000011001000000000001100010011 6
b00110 :
b10010 <
b01010101010000100100111100111100 a
1c
b00000000000000110010 g
#2
0c
#3
b00000000000000000000000000010000 #
0$
b11 %
b100 (
b10 )
b01 *
b1101111 +
b01 ,
b1011 -
b00000000000000000000000000000000 .
1/
b00000000000000000000000000000000 0
b00000000000000000000000000001000 1
12
b00000001000000000000000011101111 6
b00000000000000000000000000000100 7
b00001 :
b10000 <
1>
b00000000000000000000000000110010 G
b0000000000000100 b
1c
b00000000000000000000 g
b00000000000000000000000000010100 h
#4
0c
#5
b00000000000000000000000000000001 #
1$
b10 %
b000 (
b00 )
b00 *
b0010011 +
b00 ,
b0000 -
b00000000000000000000000000110011 .
0/
b00000000000000000000000000000001 0
b00000000000000000000000000110011 1
02
b00000000000100110000001100010011 6
b00000000000000000000000000010100 7
b00000000000000000000000000110010 8
b00000000000000000000000000001000 9
b00110 :
b00110 ;
b00001 <
0>
b00000000000000000000000000001000 B
b0000000000010100 b
1c
b00000000000000110011 g
b00000000000000000000000000011000 h
#6
0c
#7
b00000000000000000000000000000000 #
b11 %
b11 *
b1100111 +
b11 ,
b1011 -
b00000000000000000000000000001000 .
1/
b00000000000000000000000000000000 0
b00000000000000000000000000001000 1
b00000000000000001000000001100111 6
b00000000000000000000000000011000 7
b00000000000000000000000000001000 8
b00000000000000000000000000000000 9
b00000 :
b00001 ;
b00000 <
1>
b00000000000000000000000000110011 G
b0000000000011000 b
1c
b00000000000000001000 g
b00000000000000000000000000001000 h
#8
0c
#9
b00000000000000000000000000001100 #
0$
b100 (
b10 )
b01 *
b1101111 +
b01 ,
b00000000000000000000000000000000 .
b00000000000000000000000000001100 1
12
b00000000110000000000000011101111 6
b00000000000000000000000000001000 7
b00000000000000000000000000000000 8
b00001 :
b00000 ;
b01100 <
b0000000000001000 b
1c
b00000000000000000000 g
b00000000000000000000000000010100 h
#10
0c
#11
b00000000000000000000000000000001 #
1$
b10 %
b000 (
b00 )
b00 *
b0010011 +
b00 ,
b0000 -
b00000000000000000000000000110100 .
0/
b00000000000000000000000000000001 0
b00000000000000000000000000110100 1
02
b00000000000100110000001100010011 6
b00000000000000000000000000010100 7
b00000000000000000000000000110011 8
b00000000000000000000000000001100 9
b00110 :
b00110 ;
b00001 <
0>
b00000000000000000000000000001100 B
b0000000000010100 b
1c
b00000000000000110100 g
b00000000000000000000000000011000 h
#12
0c
#13
b00000000000000000000000000000000 #
b11 %
b11 *
b1100111 +
b11 ,
b1011 -
b00000000000000000000000000001100 .
1/
b00000000000000000000000000000000 0
b00000000000000000000000000001100 1
b00000000000000001000000001100111 6
b00000000000000000000000000011000 7
b00000000000000000000000000001100 8
b00000000000000000000000000000000 9
b00000 :
b00001 ;
b00000 <
1>
b00000000000000000000000000110100 G
b0000000000011000 b
1c
b00000000000000001100 g
b00000000000000000000000000001100 h
#14
0c
#15
b00000000000000000000000000001000 #
0$
b100 (
b10 )
b01 *
b1101111 +
b01 ,
b00000000000000000000000000000000 .
b00000000000000000000000000010000 1
12
b00000000100000000000000011101111 6
b00000000000000000000000000001100 7
b00000000000000000000000000000000 8
b00001 :
b00000 ;
b01000 <
b0000000000001100 b
1c
b00000000000000000000 g
b00000000000000000000000000010100 h
#16
0c
